sil_agnostic_field
